clang/staging/include/__clang_cuda_builtin_vars.h
clang/staging/include/__clang_cuda_cmath.h
clang/staging/include/__clang_cuda_complex_builtins.h
clang/staging/include/__clang_cuda_device_functions.h
clang/staging/include/__clang_cuda_intrinsics.h
clang/staging/include/__clang_cuda_libdevice_declares.h
clang/staging/include/__clang_cuda_math.h
clang/staging/include/__clang_cuda_math_forward_declares.h
clang/staging/include/__clang_cuda_runtime_wrapper.h
clang/staging/include/__clang_cuda_texture_intrinsics.h
clang/staging/include/__clang_hip_cmath.h
clang/staging/include/__clang_hip_libdevice_declares.h
clang/staging/include/__clang_hip_math.h
clang/staging/include/__clang_hip_runtime_wrapper.h
clang/staging/include/__clang_hip_stdlib.h
clang/staging/include/__stdarg___gnuc_va_list.h
clang/staging/include/__stdarg___va_copy.h
clang/staging/include/__stdarg_header_macro.h
clang/staging/include/__stdarg_va_arg.h
clang/staging/include/__stdarg_va_copy.h
clang/staging/include/__stdarg_va_list.h
clang/staging/include/__stddef_header_macro.h
clang/staging/include/__stddef_max_align_t.h
clang/staging/include/__stddef_null.h
clang/staging/include/__stddef_nullptr_t.h
clang/staging/include/__stddef_offsetof.h
clang/staging/include/__stddef_ptrdiff_t.h
clang/staging/include/__stddef_rsize_t.h
clang/staging/include/__stddef_size_t.h
clang/staging/include/__stddef_unreachable.h
clang/staging/include/__stddef_wchar_t.h
clang/staging/include/__stddef_wint_t.h
clang/staging/include/__wmmintrin_aes.h
clang/staging/include/__wmmintrin_pclmul.h
clang/staging/include/adcintrin.h
clang/staging/include/adxintrin.h
clang/staging/include/altivec.h
clang/staging/include/amdgpuintrin.h
clang/staging/include/ammintrin.h
clang/staging/include/amxavx512intrin.h
clang/staging/include/amxbf16transposeintrin.h
clang/staging/include/amxcomplexintrin.h
clang/staging/include/amxcomplextransposeintrin.h
clang/staging/include/amxfp16intrin.h
clang/staging/include/amxfp16transposeintrin.h
enzyme_ad-0.0.10.dist-info/WHEEL
enzyme_ad-0.0.10.dist-info/METADATA
enzyme_ad-0.0.10.dist-info/RECORD
