Metadata-Version: 2.1
Name: enzyme_ad
Author: Enzyme Authors
Author-email: wmoses@mit.edu, zinenko@google.com
Home-page: https://enzyme.mit.edu/
License: LLVM
Summary: Enzyme automatic differentiation tool.
Project-URL: GitHub, https://github.com/EnzymeAD/Enzyme-JAX/
Requires-Python: ==3.12.*
Requires-Dist: absl_py >= 2.0.0
Requires-Dist: jax >= 0.4.21
Requires-Dist: jaxlib >= 0.4.21
Version: 0.0.10
